nodeweb/__init__.py
nodeweb/nodeweb.py
rabbit/__init__.py
rabbit/ascii码.py
rabbit/pyuse.py
rabbit/rabbit.py
rabbit/rabbitide.py
rabbit/setup.py
rabbit/列表.py
rabbit/基本.py
rabbit/字符串.py
rabbit/游戏.py
rabbit/终端.py
rabbit/绘图.py
rabbit/运算.py
pyprabbit-1.2.2.dist-info/METADATA
pyprabbit-1.2.2.dist-info/WHEEL
pyprabbit-1.2.2.dist-info/top_level.txt
pyprabbit-1.2.2.dist-info/RECORD
