Metadata-Version: 2.1
Name: pyprabbit
Version: 1.2.2
Summary: UNKNOWN
Home-page: http://192.168.2.110:8000/index.html
Author: zhoufangfang
Author-email: xczff001@163.com
Maintainer: zhoufangfang
Maintainer-email: xczff001@163.com
License: UNKNOWN
Keywords: web,nodejs
Platform: UNKNOWN
Requires-Python: >=3
Requires-Dist: pgzero
